sdps_45m/__init__.py
sdps_45m/convert.py
sdps_45m/py.typed
sdps_45m-0.5.0.dist-info/METADATA
sdps_45m-0.5.0.dist-info/WHEEL
sdps_45m-0.5.0.dist-info/entry_points.txt
sdps_45m-0.5.0.dist-info/licenses/LICENSE
sdps_45m-0.5.0.dist-info/RECORD
