Metadata-Version: 2.4
Name: sdps-45m
Version: 0.5.0
Summary: Tools of sdps for the Nobeyama 45m Telescope
Project-URL: repository, https://github.com/sdps-dev/45m
Author-email: Akio Taniguchi <taniguchi.akio@gmail.com>
License: MIT License
License-File: LICENSE
Classifier: License :: OSI Approved :: MIT License
Classifier: Programming Language :: Python :: 3
Classifier: Programming Language :: Python :: 3.10
Classifier: Programming Language :: Python :: 3.11
Classifier: Programming Language :: Python :: 3.12
Requires-Python: <3.13,>=3.10
Requires-Dist: astropy<8,>=6
Requires-Dist: bottleneck<2,>=1
Requires-Dist: decode<2026,>=2025
Requires-Dist: dems<2026,>=2025
Requires-Dist: fire<1.0,>=0.7
Requires-Dist: fmflow<1.0,>=0.5
Requires-Dist: ndtools<2,>=1
Requires-Dist: numpy<3,>=2
Requires-Dist: xarray<2026,>=2024
Requires-Dist: zarr<3,>=2
